map_analyzer/__init__.py
map_analyzer/cli/__init__.py
map_analyzer/cli/map_analyzer.py
map_analyzer/models/__init__.py
map_analyzer/models/core_group.py
map_analyzer/models/detail_group.py
map_analyzer/models/detail_item.py
map_analyzer/models/file_property.py
map_analyzer/models/section.py
map_analyzer/parser/__init__.py
map_analyzer/parser/config_parser.py
map_analyzer/parser/map.py
map_analyzer/parser/map_gcc.py
map_analyzer/parser/map_ghs.py
map_analyzer/reporter/__init__.py
map_analyzer/reporter/excel_report.py
map_reporter/__init__.py
map_reporter/cli/__init__.py
map_reporter/cli/map_report.py
map_reporter/cli/map_reporter.py
map_analyzer-0.2.1.dist-info/LICENSE
map_analyzer-0.2.1.dist-info/METADATA
map_analyzer-0.2.1.dist-info/WHEEL
map_analyzer-0.2.1.dist-info/entry_points.txt
map_analyzer-0.2.1.dist-info/top_level.txt
map_analyzer-0.2.1.dist-info/RECORD
