Metadata-Version: 2.1
Name: map-analyzer
Version: 0.2.1
Summary: A Python tool for GHS map analysis
Home-page: https://github.com/melodypapa/py-map-analyzer
Author: Melodypapa
Author-email: melodypapa@outlook.com
License: MIT
Keywords: GHS Map
Platform: UNKNOWN
Classifier: Development Status :: 1 - Planning
Classifier: Environment :: Console
Classifier: Programming Language :: Python :: 3
Classifier: License :: OSI Approved :: MIT License
Classifier: Operating System :: OS Independent
Requires-Python: >=3.5
Requires-Dist: toml
Requires-Dist: openpyxl
Provides-Extra: pytest
Requires-Dist: pytest-cov ; extra == 'pytest'
